setup.py
digUrlLocalityExtractor/__init__.py
digUrlLocalityExtractor/url_locality_extractor.py
digUrlLocalityExtractor.egg-info/PKG-INFO
digUrlLocalityExtractor.egg-info/SOURCES.txt
digUrlLocalityExtractor.egg-info/dependency_links.txt
digUrlLocalityExtractor.egg-info/requires.txt
digUrlLocalityExtractor.egg-info/top_level.txt