Metadata-Version: 1.1
Name: digUrlLocalityExtractor
Version: 0.3.0
Summary: digUrlLocalityExtractor
Home-page: https://github.com/usc-isi-i2/dig-url-locality-extractor
Author: Vinay Rao Dandin
Author-email: vrdandin@isi.edu
License: UNKNOWN
Download-URL: https://github.com/usc-isi-i2/dig-url-locality-extractor
Platform: UNKNOWN
